phext/__init__.py
phext/coordinate.py
phext/phext.py
phext/positionedScroll.py
phext/range.py
phext-0.3.0.dist-info/METADATA
phext-0.3.0.dist-info/WHEEL
phext-0.3.0.dist-info/RECORD
